{
  "main": {
    "id": "cb588626270f8fe8",
    "type": "split",
    "children": [
      {
        "id": "6299d26c63ea6ec0",
        "type": "tabs",
        "children": [
          {
            "id": "e49bdbdbcbf97b62",
            "type": "leaf",
            "state": {
              "type": "markdown",
              "state": {
                "file": "README.md",
                "mode": "source",
                "source": false
              }
            }
          }
        ]
      }
    ],
    "direction": "vertical"
  },
  "left": {
    "id": "8529fb544df1d6ca",
    "type": "split",
    "children": [
      {
        "id": "22c91f0a172e1877",
        "type": "tabs",
        "children": [
          {
            "id": "a81772418df350af",
            "type": "leaf",
            "state": {
              "type": "file-explorer",
              "state": {
                "sortOrder": "alphabetical"
              }
            }
          },
          {
            "id": "5e544fdae4368034",
            "type": "leaf",
            "state": {
              "type": "search",
              "state": {
                "query": "",
                "matchingCase": false,
                "explainSearch": false,
                "collapseAll": false,
                "extraContext": false,
                "sortOrder": "alphabetical"
              }
            }
          },
          {
            "id": "c475d8052033a325",
            "type": "leaf",
            "state": {
              "type": "starred",
              "state": {}
            }
          }
        ]
      }
    ],
    "direction": "horizontal",
    "width": 300
  },
  "right": {
    "id": "2fbed0b9fdfabc84",
    "type": "split",
    "children": [
      {
        "id": "b48cb5c56924a4e8",
        "type": "tabs",
        "children": [
          {
            "id": "0f6e7fbeb24c63cb",
            "type": "leaf",
            "state": {
              "type": "backlink",
              "state": {
                "file": "README.md",
                "collapseAll": false,
                "extraContext": false,
                "sortOrder": "alphabetical",
                "showSearch": false,
                "searchQuery": "",
                "backlinkCollapsed": false,
                "unlinkedCollapsed": true
              }
            }
          },
          {
            "id": "d78f6d40a50ded82",
            "type": "leaf",
            "state": {
              "type": "outgoing-link",
              "state": {
                "file": "README.md",
                "linksCollapsed": false,
                "unlinkedCollapsed": true
              }
            }
          },
          {
            "id": "1ed1dd39a1e2aee3",
            "type": "leaf",
            "state": {
              "type": "tag",
              "state": {
                "sortOrder": "frequency",
                "useHierarchy": true
              }
            }
          },
          {
            "id": "76274fdd70d199f7",
            "type": "leaf",
            "state": {
              "type": "outline",
              "state": {
                "file": "README.md"
              }
            }
          }
        ]
      }
    ],
    "direction": "horizontal",
    "width": 300,
    "collapsed": true
  },
  "active": "e49bdbdbcbf97b62",
  "lastOpenFiles": [
    "Git.md",
    "NPM.md",
    "WSL.md",
    "README.md",
    "CMD.md",
    "local/wp.jpg"
  ]
}